MANIFEST.in
setup.cfg
setup.py
oh_my_vim.egg-info/PKG-INFO
oh_my_vim.egg-info/SOURCES.txt
oh_my_vim.egg-info/dependency_links.txt
oh_my_vim.egg-info/entry_points.txt
oh_my_vim.egg-info/not-zip-safe
oh_my_vim.egg-info/requires.txt
oh_my_vim.egg-info/top_level.txt
ohmyvim/__init__.py
ohmyvim/config.ini
ohmyvim/fpcli.py
ohmyvim/scripts.py
ohmyvim/tests.py