Metadata-Version: 1.0
Name: oh-my-vim
Version: 0.6
Summary: Vim plugin manager and Vim related stuff
Home-page: https://github.com/gawel/oh-my-vim
Author: Gael Pasgrimaud
Author-email: gael@gawel.org
License: GPL
Keywords: vim pathogen
Platform: UNKNOWN
Classifier: Environment :: Console
Classifier: Intended Audience :: Developers
Classifier: License :: OSI Approved :: GNU General Public License (GPL)
Classifier: Topic :: Software Development
Classifier: Topic :: Text Editors
